{
    "DNDConfig": null,
    "__parentReadjusting__": false,
    "_height_": {
        "type": "string",
        "value": "100%"
    },
    "_left_": {
        "type": "string",
        "value": "75dp"
    },
    "_margin_": [
        0,
        0,
        0,
        0
    ],
    "_orientation_": 6,
    "_padding_": [
        0,
        0,
        0,
        0
    ],
    "_percent_": true,
    "_skin_": "sf61e8ca19bd4757b711104847b6c13a",
    "_top_": {
        "type": "string",
        "value": "0dp"
    },
    "_width_": {
        "type": "string",
        "value": "20%"
    },
    "allboxes": [],
    "autogrowmode": 0,
    "canUpdateUI": true,
    "children": [
        "CopybtnFolder0gbdb5c121d5f4c",
        "CopytvFile0b91d3660ba9b41"
    ],
    "clipbounds": true,
    "containerweight": 100,
    "enablescrolling": true,
    "id": "CopyFlexContainer0dbc93143e58c45",
    "ide_onClick": "AS_FlexContainer_g89e7165acf840b48d013aad23cc3423",
    "info": null,
    "isvisible": true,
    "kuid": "f0c933513b5b4882af9c573b094c0c52",
    "layouttype": 2,
    "masterType": 1,
    "name": "kony.ui.FlexContainer",
    "parent": "footerEditToolbar2",
    "pf": "Form5",
    "snapgridsize": 10,
    "snaptogrid": true,
    "wType": "FlexContainer",
    "widgetalignment": 1,
    "zindex": 1
}